grob/__init__.py
grob/cli/__init__.py
grob/cli/app.py
grob/core/__init__.py
grob/core/errors.py
grob/core/files.py
grob/core/finder.py
grob/core/frozendict.py
grob/core/group_validation.py
grob/core/key_formatters.py
grob/core/output_formatters.py
grob/core/output_writers.py
grob/core/parsers.py
grob/core/tags.py
grob/core/walker.py
grob/types.py
grob-0.2.1.dist-info/LICENSE
grob-0.2.1.dist-info/METADATA
grob-0.2.1.dist-info/WHEEL
grob-0.2.1.dist-info/entry_points.txt
grob-0.2.1.dist-info/RECORD
