Metadata-Version: 2.1
Name: grob
Version: 0.2.1
Summary: Group files together in a breeze with glob-like patterns
Home-page: https://github.com/felix-martel/grob
Author: Félix Martel
Author-email: ffelix.martel@polytechnique.edu
Requires-Python: >=3.8,<4.0
Classifier: Programming Language :: Python :: 3
Classifier: Programming Language :: Python :: 3.8
Classifier: Programming Language :: Python :: 3.9
Classifier: Programming Language :: Python :: 3.10
Classifier: Programming Language :: Python :: 3.11
Classifier: Programming Language :: Python :: 3.12
Project-URL: Documentation, https://felix-martel.github.io/grob/
Project-URL: Repository, https://github.com/felix-martel/grob
